test_pip/__init__.py
test_pip/test.py
test_pip-1.0.0.dist-info/LICENSE
test_pip-1.0.0.dist-info/METADATA
test_pip-1.0.0.dist-info/WHEEL
test_pip-1.0.0.dist-info/top_level.txt
test_pip-1.0.0.dist-info/RECORD
