Metadata-Version: 2.1
Name: test-pip
Version: 1.0.0
Summary: ??
Home-page: https://github.com/ljhandlwt/fpsp
Author: jh
Author-email: a@qq.com
License: UNKNOWN
Platform: UNKNOWN
Classifier: Programming Language :: Python :: 3
Classifier: License :: OSI Approved :: MIT License
Classifier: Operating System :: OS Independent
